noat_test/__init__.py
noat_test/example.py
example_pkg_scdev_pd_columns_noah2-0.0.2.dist-info/LICENSE.txt
example_pkg_scdev_pd_columns_noah2-0.0.2.dist-info/METADATA
example_pkg_scdev_pd_columns_noah2-0.0.2.dist-info/WHEEL
example_pkg_scdev_pd_columns_noah2-0.0.2.dist-info/top_level.txt
example_pkg_scdev_pd_columns_noah2-0.0.2.dist-info/RECORD
